semantic_chunking/__init__.py
semantic_chunking/main.py
semantic_chunking-0.1.1.dist-info/METADATA
semantic_chunking-0.1.1.dist-info/WHEEL
semantic_chunking-0.1.1.dist-info/top_level.txt
semantic_chunking-0.1.1.dist-info/RECORD
