Metadata-Version: 2.1
Name: semantic_chunking
Version: 0.1.1
Summary: A Python library for semantic text chunking using Sentence Transformers.
Home-page: https://github.com/thanhhung2112/semantic_chunking
Author: Le Thanh Hung
Author-email: lthung2112@gmail.com
Classifier: Programming Language :: Python :: 3
Classifier: License :: OSI Approved :: MIT License
Classifier: Operating System :: OS Independent
Requires-Python: >=3.8
Requires-Dist: numpy>=1.18.5
Requires-Dist: sentence-transformers>=2.2.2
